rigup/__init__.py
rigup/_utils.py
rigup/cluster/__init__.py
rigup/cluster/manager.py
rigup/cluster/node.py
rigup/cluster/protocol.py
rigup/cluster/transport/__init__.py
rigup/cluster/transport/adapter.py
rigup/cluster/transport/comm.py
rigup/cluster/transport/service.py
rigup/device/__init__.py
rigup/device/base.py
rigup/device/build.py
rigup/device/controller.py
rigup/device/handle.py
rigup/device/props/__init__.py
rigup/device/props/common.py
rigup/device/props/deliminated.py
rigup/device/props/enumerated.py
rigup/local.py
rigup/rig.py
rigup-0.1.0.dist-info/WHEEL
rigup-0.1.0.dist-info/METADATA
rigup-0.1.0.dist-info/RECORD
