Metadata-Version: 2.4
Name: rigup
Version: 0.1.0
Summary: Distributed device control for experimental rigs
Keywords: device-control,hardware,zmq,distributed,rig,pyrig,voxel,vxl
Author: Walter Mwaniki
Author-email: Walter Mwaniki <walter.g.mwaniki@gmail.com>
License-Expression: MIT
Classifier: Development Status :: 3 - Alpha
Classifier: Intended Audience :: Science/Research
Classifier: Topic :: Scientific/Engineering
Classifier: Topic :: System :: Hardware
Requires-Dist: pydantic>=2.12.0
Requires-Dist: pyzmq>=27.1.0
Requires-Dist: ruyaml>=0.91.0
Requires-Python: >=3.13
Project-URL: Repository, https://github.com/AllenNeuralDynamics/voxel
Project-URL: Issues, https://github.com/AllenNeuralDynamics/voxel/issues
